spire/__init__.py
spire/presentation/ActiveSlide.py
spire/presentation/AppException.py
spire/presentation/AudioCD.py
spire/presentation/AudioPlayMode.py
spire/presentation/AudioVolumeType.py
spire/presentation/BaseShapeLocking.py
spire/presentation/Camera.py
spire/presentation/ClickHyperlink.py
spire/presentation/Comment.py
spire/presentation/ConnectorLocking.py
spire/presentation/DefaultTextRangeProperties.py
spire/presentation/Direction.py
spire/presentation/Field.py
spire/presentation/FieldType.py
spire/presentation/FileFormat.py
spire/presentation/FontAlignmentType.py
spire/presentation/FontCollectionIndex.py
spire/presentation/FontScheme.py
spire/presentation/FormatAndVersion.py
spire/presentation/GroupShape.py
spire/presentation/GroupShapeLocking.py
spire/presentation/HyperlinkActionType.py
spire/presentation/IActivePresentation.py
spire/presentation/IActiveSlide.py
spire/presentation/IAudio.py
spire/presentation/IAudioData.py
spire/presentation/IAutoShape.py
spire/presentation/ICommentAuthor.py
spire/presentation/IDigitalSignature.py
spire/presentation/IDigitalSignatures.py
spire/presentation/IDocumentProperty.py
spire/presentation/IEmbedImage.py
spire/presentation/ILayout.py
spire/presentation/IMasterSlide.py
spire/presentation/INoteMasterSlide.py
spire/presentation/IOleObject.py
spire/presentation/IShape.py
spire/presentation/ISlide.py
spire/presentation/ITextFrameProperties.py
spire/presentation/IVideo.py
spire/presentation/ImportDataFormat.py
spire/presentation/InsertPlaceholderType.py
spire/presentation/KnownColors.py
spire/presentation/LightRig.py
spire/presentation/LightingDirectionType.py
spire/presentation/LineCapStyle.py
spire/presentation/LineDashStyleType.py
spire/presentation/LineEndLength.py
spire/presentation/LineEndType.py
spire/presentation/LineEndWidth.py
spire/presentation/LineFillFormat.py
spire/presentation/LineJoinType.py
spire/presentation/LineText.py
spire/presentation/LinearGradientFill.py
spire/presentation/LocaleFonts.py
spire_presentation-11.1.0.dist-info/METADATA
spire_presentation-11.1.0.dist-info/WHEEL
spire_presentation-11.1.0.dist-info/top_level.txt
spire_presentation-11.1.0.dist-info/RECORD
